<?xml version="1.0" encoding="UTF-8"?>
<metadata xml:lang="en"><Esri><CreaDate>20180730</CreaDate><CreaTime>21592200</CreaTime><ArcGISFormat>1.0</ArcGISFormat><SyncOnce>TRUE</SyncOnce><DataProperties><lineage><Process ToolSource="c:\program files (x86)\arcgis\desktop10.2\ArcToolbox\Toolboxes\Data Management Tools.tbx\CalculateField" Date="20171013" Time="192927">CalculateField Strata_basic_LCC ProvState Left(Right( [St_12],5  ),2) VB #</Process><Process ToolSource="c:\program files (x86)\arcgis\desktop10.2\ArcToolbox\Toolboxes\Data Management Tools.tbx\CalculateField" Date="20171013" Time="193145">CalculateField Strata_basic_LCC ProvState Right( [St_12],5  ) VB #</Process><Process ToolSource="c:\program files (x86)\arcgis\desktop10.2\ArcToolbox\Toolboxes\Data Management Tools.tbx\CalculateField" Date="20171013" Time="193222">CalculateField Strata_basic_LCC ProvState Left( [St_12],5  ) VB #</Process><Process ToolSource="c:\program files (x86)\arcgis\desktop10.2\ArcToolbox\Toolboxes\Data Management Tools.tbx\CalculateField" Date="20171013" Time="193249">CalculateField Strata_basic_LCC ProvState Right(Left( [St_12],5  ),2) VB #</Process><Process ToolSource="c:\program files (x86)\arcgis\desktop10.2\ArcToolbox\Toolboxes\Data Management Tools.tbx\CalculateField" Date="20171013" Time="193340">CalculateField Strata_basic_LCC Country Left( [St_12],2) VB #</Process></lineage></DataProperties></Esri></metadata>
